{
  "books": [
    {
      "id": 1,
      "title": "To Kill a Mockingbird",
      "author": "Harper Lee",
      "genre": "Fiction",
      "publicationYear": 1960,
      "rating": 4.8,
      "description": "A novel about serious issues of rape and racial inequality."
    },
    {
      "id": 2,
      "title": "1984",
      "author": "George Orwell",
      "genre": "Dystopian",
      "publicationYear": 1949,
      "rating": 4.7,
      "description": "A story about a dystopian future under a totalitarian regime."
    },
    {
      "id": 3,
      "title": "The Great Gatsby",
      "author": "F. Scott Fitzgerald",
      "genre": "Fiction",
      "publicationYear": 1925,
      "rating": 4.4,
      "description": "A novel about the American dream and disillusionment."
    },
    {
      "id": 4,
      "title": "Moby Dick",
      "author": "Herman Melville",
      "genre": "Adventure",
      "publicationYear": 1851,
      "rating": 4.2,
      "description": "A quest to capture the elusive white whale."
    },
    {
      "id": 5,
      "title": "Pride and Prejudice",
      "author": "Jane Austen",
      "genre": "Romance",
      "publicationYear": 1813,
      "rating": 4.6,
      "description": "A novel exploring themes of love and social class."
    }
  ],
  "products": [],
  "users": []
}
